LICENSE.txt
MANIFEST.in
README.rst
setup.py
django_tumblr_auth.egg-info/PKG-INFO
django_tumblr_auth.egg-info/SOURCES.txt
django_tumblr_auth.egg-info/dependency_links.txt
django_tumblr_auth.egg-info/requires.txt
django_tumblr_auth.egg-info/top_level.txt
tumblr_auth/__init__.py
tumblr_auth/backend.py
tumblr_auth/models.py
tumblr_auth/tests.py
tumblr_auth/views.py