Metadata-Version: 1.0
Name: django-tumblr-auth
Version: 0.0.1
Summary: django-tumblr-auth is an extension to django-social-auth which adds a backend for Tumblr.com.
Home-page: https://github.com/alageek/django-tumblr-auth
Author: Gökmen Görgen
Author-email: gokmen@alageek.com
License: BSD
Platform: UNKNOWN
Classifier: Topic :: Internet :: WWW/HTTP :: Dynamic Content
Classifier: Intended Audience :: Developers
Classifier: License :: OSI Approved :: BSD License
Classifier: Programming Language :: Python
Classifier: Topic :: Software Development :: Libraries :: Python Modules
Classifier: Development Status :: 4 - Beta
Classifier: Operating System :: OS Independent
